Mzhtools/Mzhtools.py
Mzhtools/__init__.py
Mzhtools-5.1.1.dist-info/METADATA
Mzhtools-5.1.1.dist-info/WHEEL
Mzhtools-5.1.1.dist-info/top_level.txt
Mzhtools-5.1.1.dist-info/RECORD
