Metadata-Version: 2.1
Name: Mzhtools
Version: 5.1.1
Summary: Python helper tools
Home-page: https://pypi.org/project/Mzhtools/
Author: Author's name
Author-email: 191891173@qq.com
Classifier: Programming Language :: Python :: 3
Classifier: License :: OSI Approved :: MIT License
Classifier: Operating System :: OS Independent
